<?xml version="1.0" encoding="utf-8" ?>
<Sala>
	<Periodos>


		<Periodo>
			<Nombre>
				PERIODO INTERMEDIO TARDÍO - EL REINO COLLA
			</Nombre>
			<Epoca>800 a 1400 d. C.</Epoca>
			<Descripcion>

				Se desarrolla en el Altiplano, a orillas del Lago Titicaca, su capital era JATUNCOLLA y su cementerio real estaba en Sillustani (PUNO).
Al no poder tener todos los productos necesarios en esa altura, enviaron colonias altiplánicas a los valles interandinos y costeños a fin de cultivar productos como el ají, algodón, variedad de maíz asi como la recolección de mariscos, el cochayuyo y el pescado que era secado y trasladado.
Su cerámica estaba decorada con motivos geométricos, utiliza la técnica de pintura pre – cocción y el color negro aplicado sobre la arcilla sin engobe.
Evidencias de la presencia Colla en Arequipa la encontramos a lo largo de los Valles del Colca, Majes y Camaná.
Sus fardos funerarios son hechos en base a paja de puna o ichu.
			</Descripcion>
		</Periodo>


	</Periodos>
	
</Sala>